Metadata-Version: 2.2
Name: ewoksoptics
Version: 0.1.0
Summary: Ewoks tasks for automation of speckle tracking metrology on ID06 and BM05
Home-page: https://gitlab.esrf.fr/workflow/ewoksoptics/
Author: ESRF
Author-email: marjolaine.bodin@esrf.fr
License: MIT
Project-URL: Source, https://gitlab.esrf.fr/workflow/ewoksoptics/
Project-URL: Documentation, https://ewoksoptics.readthedocs.io/
Project-URL: Tracker, https://gitlab.esrf.fr/workflow/ewoksoptics/issues/
Keywords: ewoks
Classifier: Intended Audience :: Science/Research
Classifier: License :: OSI Approved :: MIT License
Classifier: Programming Language :: Python :: 3
Requires-Python: >=3.7
License-File: LICENSE.md
Requires-Dist: ewokscore
Provides-Extra: test
Requires-Dist: pytest>=7; extra == "test"
Provides-Extra: dev
Requires-Dist: pytest>=7; extra == "dev"
Requires-Dist: black>=22; extra == "dev"
Requires-Dist: flake8>=4; extra == "dev"
Provides-Extra: doc
Requires-Dist: pytest>=7; extra == "doc"
Requires-Dist: sphinx>=4.5; extra == "doc"
Requires-Dist: sphinx-autodoc-typehints>=1.16; extra == "doc"
Requires-Dist: pydata-sphinx-theme<0.15; extra == "doc"
